qx/__init__.py
qx/__main__.py
qx/encodings/xor.py
qx/file/header.py
qx-0.1.0.dist-info/LICENSE
qx-0.1.0.dist-info/WHEEL
qx-0.1.0.dist-info/METADATA
qx-0.1.0.dist-info/RECORD
