Metadata-Version: 2.1
Name: qx
Version: 0.1.0
Summary: A tool and file format for encoding and decoding data with an ASCII key
License: GPLv3
Author: Evan Pratten
Author-email: ewpratten@gmail.com
Requires-Python: >=3.6,<4.0
Classifier: License :: Other/Proprietary License
Classifier: Programming Language :: Python :: 3
Classifier: Programming Language :: Python :: 3.6
Classifier: Programming Language :: Python :: 3.7
Classifier: Programming Language :: Python :: 3.8
Classifier: Programming Language :: Python :: 3.9
